raycast2d-0.2.0.dist-info/RECORD
raycast2d-0.2.0.dist-info/WHEEL
raycast2d-0.2.0.dist-info/top_level.txt
raycast2d-0.2.0.dist-info/METADATA
raycast2d-0.2.0.dist-info/licenses/LICENSE
raycast2D/raycast2D.py
raycast2D/_raycastermodule.c
raycast2D/__init__.py
raycast2D/raycaster.cpython-312-darwin.so
