Metadata-Version: 2.4
Name: raycast2D
Version: 0.2.0
Summary: A fast image-based 2D raycasting library.
Author-email: Matteo Princisgh <princisgh@gmail.com>
License-Expression: GPL-3.0-only
Project-URL: Homepage, https://github.com/prina404/raycast2D
Keywords: raycasting,lidar,raycasting2D,robotics
Classifier: Programming Language :: Python
Classifier: Programming Language :: Python :: 3
Classifier: Programming Language :: Python :: 3.10
Classifier: Programming Language :: Python :: 3.11
Classifier: Programming Language :: Python :: 3.12
Classifier: Programming Language :: Python :: 3.13
Classifier: Programming Language :: Python :: 3.14
Classifier: Operating System :: OS Independent
Requires-Python: <3.15,>=3.10
License-File: LICENSE
Requires-Dist: numpy>=1.25
Provides-Extra: extra
Requires-Dist: pillow; extra == "extra"
Requires-Dist: pygame; extra == "extra"
Provides-Extra: test
Requires-Dist: pytest; extra == "test"
Requires-Dist: build; extra == "test"
Dynamic: description
Dynamic: description-content-type
Dynamic: license-file
